fireants/__init__.py
fireants/dispatcher.py
fireants/types.py
fireants/interpolator/__init__.py
fireants/interpolator/fused_grid_sample.py
fireants/interpolator/grid_sample.py
fireants/io/__init__.py
fireants/io/image.py
fireants/io/transform.py
fireants/losses/__init__.py
fireants/losses/cc.py
fireants/losses/fusedcc.py
fireants/losses/fusedmi.py
fireants/losses/mi.py
fireants/losses/mse.py
fireants/notebooks/Inverse transformation.py
fireants/notebooks/cuda_gridsample_grad2_py19/cuda_gridsample.py
fireants/notebooks/cuda_gridsample_grad2_py19/naive_gridsample.py
fireants/notebooks/cuda_gridsample_grad2_py19/setup.py
fireants/notebooks/cuda_gridsample_grad2_py19/stylegan_gridsample.py
fireants/notebooks/cuda_gridsample_grad2_py19/test2d.py
fireants/notebooks/cuda_gridsample_grad2_py19/test3d.py
fireants/registration/__init__.py
fireants/registration/abstract.py
fireants/registration/affine.py
fireants/registration/deformablemixin.py
fireants/registration/distributedgreedy.py
fireants/registration/greedy.py
fireants/registration/moments.py
fireants/registration/rigid.py
fireants/registration/syn.py
fireants/registration/deformation/abstract.py
fireants/registration/deformation/compositive.py
fireants/registration/deformation/compositivedistributed.py
fireants/registration/deformation/svf.py
fireants/registration/distributed/parallel_state.py
fireants/registration/distributed/ring_sampler.py
fireants/registration/distributed/test_dp_gp.py
fireants/registration/distributed/utils.py
fireants/registration/optimizers/adam.py
fireants/registration/optimizers/sgd.py
fireants/scripts/evaluate_metrics.py
fireants/scripts/evalutils.py
fireants/scripts/lookup_tables.py
fireants/scripts/hyperparameter_tuning/analyse_raytune.py
fireants/scripts/hyperparameter_tuning/tune_empire10.py
fireants/scripts/hyperparameter_tuning/tune_lpba40.py
fireants/scripts/misc/mi_torch_compile.py
fireants/scripts/misc/cumc12/save_cumc12_outputs.py
fireants/scripts/misc/fMOST/affine_prealign.py
fireants-1.0.0.dist-info/licenses/LICENSE
fireants-1.0.0.dist-info/METADATA
fireants-1.0.0.dist-info/WHEEL
fireants-1.0.0.dist-info/top_level.txt
fireants-1.0.0.dist-info/RECORD
