Metadata-Version: 2.4
Name: fireants
Version: 1.0.0
Summary: FireANTs: Adaptive Riemannian Optimization for Multi-Scale Diffeomorphic Registration
Author: Rohit Jena, Pratik Chaudhari, James C. Gee
Requires-Python: >=3.7
License-File: LICENSE
Requires-Dist: torch>=2.3.0
Requires-Dist: SimpleITK==2.2.1
Requires-Dist: nibabel
Requires-Dist: numpy
Requires-Dist: scipy
Requires-Dist: scikit-image
Requires-Dist: matplotlib
Requires-Dist: typing
Requires-Dist: tqdm
Requires-Dist: pandas
Requires-Dist: hydra-core
Dynamic: license-file
